LICENSE.txt
MANIFEST.in
README.md
setup.py
ppsqlviz/__init__.py
ppsqlviz/plotter.py
ppsqlviz.egg-info/PKG-INFO
ppsqlviz.egg-info/SOURCES.txt
ppsqlviz.egg-info/dependency_links.txt
ppsqlviz.egg-info/requires.txt
ppsqlviz.egg-info/top_level.txt