Metadata-Version: 1.0
Name: ppsqlviz
Version: 1.0
Summary: A command line visualization utility for SQL using Pandas library in Python.
Home-page: http://vatsan.github.io/pandas_via_psql/
Author: Srivatsan Ramanujam
Author-email: vatsan.cs@utexas.edu
License: LICENSE.txt
Platform: UNKNOWN
